<?xml version="1.0" encoding="UTF-8" standalone="yes"?>
<model type="com.apple.IDECoreDataModeler.DataModel" documentVersion="1.0" lastSavedToolsVersion="21754" systemVersion="22D68" minimumToolsVersion="Automatic" sourceLanguage="Swift" userDefinedModelVersionIdentifier="">
    <entity name="ProductData" representedClassName="ProductData" syncable="YES" codeGenerationType="class">
        <attribute name="category" optional="YES" attributeType="Binary"/>
        <attribute name="desc" optional="YES" attributeType="String"/>
        <attribute name="images" optional="YES" attributeType="Binary"/>
        <attribute name="price" optional="YES" attributeType="Double" defaultValueString="0.0" usesScalarValueType="YES"/>
        <attribute name="productId" attributeType="Integer 64" defaultValueString="0" usesScalarValueType="YES"/>
        <attribute name="title" optional="YES" attributeType="String"/>
    </entity>
    <entity name="ProfileData" representedClassName="ProfileData" syncable="YES" codeGenerationType="class">
        <attribute name="data" optional="YES" attributeType="Binary"/>
    </entity>
</model>